pydra/tasks/fsl/__init__.py
pydra/tasks/fsl/_version.py
pydra/tasks/fsl/latest.py
pydra/tasks/fsl/auto/__init__.py
pydra/tasks/fsl/auto/_post_release.py
pydra/tasks/fsl/auto/aroma/__init__.py
pydra/tasks/fsl/auto/aroma/ica__aroma.py
pydra/tasks/fsl/auto/aroma/tests/conftest.py
pydra/tasks/fsl/auto/aroma/tests/test_ica_aroma.py
pydra/tasks/fsl/auto/dti/__init__.py
pydra/tasks/fsl/auto/dti/bedpostx5.py
pydra/tasks/fsl/auto/dti/distance_map.py
pydra/tasks/fsl/auto/dti/dti_fit.py
pydra/tasks/fsl/auto/dti/find_the_biggest.py
pydra/tasks/fsl/auto/dti/make_dyadic_vectors.py
pydra/tasks/fsl/auto/dti/prob_track_x.py
pydra/tasks/fsl/auto/dti/prob_track_x2.py
pydra/tasks/fsl/auto/dti/proj_thresh.py
pydra/tasks/fsl/auto/dti/tract_skeleton.py
pydra/tasks/fsl/auto/dti/vec_reg.py
pydra/tasks/fsl/auto/dti/x_fibres_5.py
pydra/tasks/fsl/auto/dti/tests/conftest.py
pydra/tasks/fsl/auto/dti/tests/test_bedpostx5.py
pydra/tasks/fsl/auto/dti/tests/test_distancemap.py
pydra/tasks/fsl/auto/dti/tests/test_dtifit.py
pydra/tasks/fsl/auto/dti/tests/test_findthebiggest.py
pydra/tasks/fsl/auto/dti/tests/test_makedyadicvectors.py
pydra/tasks/fsl/auto/dti/tests/test_probtrackx.py
pydra/tasks/fsl/auto/dti/tests/test_probtrackx2.py
pydra/tasks/fsl/auto/dti/tests/test_projthresh.py
pydra/tasks/fsl/auto/dti/tests/test_tractskeleton.py
pydra/tasks/fsl/auto/dti/tests/test_vecreg.py
pydra/tasks/fsl/auto/dti/tests/test_xfibres5.py
pydra/tasks/fsl/auto/epi/__init__.py
pydra/tasks/fsl/auto/epi/apply_topup.py
pydra/tasks/fsl/auto/epi/eddy.py
pydra/tasks/fsl/auto/epi/eddy_correct.py
pydra/tasks/fsl/auto/epi/eddy_quad.py
pydra/tasks/fsl/auto/epi/epi_de_warp.py
pydra/tasks/fsl/auto/epi/epi_reg.py
pydra/tasks/fsl/auto/epi/prepare_fieldmap.py
pydra/tasks/fsl/auto/epi/topup.py
pydra/tasks/fsl/auto/epi/tests/conftest.py
pydra/tasks/fsl/auto/epi/tests/test_applytopup.py
pydra/tasks/fsl/auto/epi/tests/test_eddy.py
pydra/tasks/fsl/auto/epi/tests/test_eddycorrect.py
pydra/tasks/fsl/auto/epi/tests/test_eddyquad.py
pydra_fsl-0.1.1.dist-info/METADATA
pydra_fsl-0.1.1.dist-info/WHEEL
pydra_fsl-0.1.1.dist-info/licenses/LICENSE
pydra_fsl-0.1.1.dist-info/licenses/NOTICE
pydra_fsl-0.1.1.dist-info/RECORD
