Metadata-Version: 2.3
Name: pydra-fsl
Version: 0.1.1
Summary: Pydra tasks package for fsl
Project-URL: Documentation, https://github.com/nipype/pydra-tasks-fsl#readme
Project-URL: Issues, https://github.com/nipype/pydra-tasks-fsl/issues
Project-URL: Source, https://github.com/nipype/pydra-tasks-fsl
Author-email: Nipype developers <neuroimaging@python.org>, Ghislain Vaillant <ghislain.vaillant@icm-institute.org>
Maintainer-email: Nipype developers <neuroimaging@python.org>, Ghislain Vaillant <ghislain.vaillant@icm-institute.org>
License:                                  Apache License
License-File: LICENSE
License-File: NOTICE
Keywords: fsl,neuroimaging,pydra
Classifier: Development Status :: 3 - Alpha
Classifier: Intended Audience :: Science/Research
Classifier: License :: OSI Approved :: Apache Software License
Classifier: Operating System :: OS Independent
Classifier: Programming Language :: Python :: 3
Classifier: Programming Language :: Python :: 3.7
Classifier: Programming Language :: Python :: 3.8
Classifier: Programming Language :: Python :: 3.9
Classifier: Programming Language :: Python :: 3.10
Classifier: Programming Language :: Python :: 3.11
Classifier: Topic :: Scientific/Engineering
Classifier: Topic :: Software Development :: Libraries
Requires-Python: >=3.8
Requires-Dist: fileformats-datascience>=0.1
Requires-Dist: fileformats-medimage-fsl
Requires-Dist: fileformats-medimage>=0.4.1
Requires-Dist: fileformats>=0.8.3
Requires-Dist: pydra>=0.22
Provides-Extra: dev
Requires-Dist: black; extra == 'dev'
Requires-Dist: pre-commit; extra == 'dev'
Provides-Extra: doc
Requires-Dist: packaging; extra == 'doc'
Requires-Dist: pydata-sphinx-theme>=0.13; extra == 'doc'
Requires-Dist: sphinx-rtd-theme; extra == 'doc'
Requires-Dist: sphinx>=2.1.2; extra == 'doc'
Requires-Dist: sphinxcontrib-apidoc~=0.3.0; extra == 'doc'
Requires-Dist: sphinxcontrib-napoleon; extra == 'doc'
Requires-Dist: sphinxcontrib-versioning; extra == 'doc'
Provides-Extra: test
Requires-Dist: codecov; extra == 'test'
Requires-Dist: fileformats-datascience-extras; extra == 'test'
Requires-Dist: fileformats-extras; extra == 'test'
Requires-Dist: fileformats-medimage-extras; extra == 'test'
Requires-Dist: fileformats-medimage-fsl-extras; extra == 'test'
Requires-Dist: nipype2pydra; extra == 'test'
Requires-Dist: pytest-cov; extra == 'test'
Requires-Dist: pytest-env; extra == 'test'
Requires-Dist: pytest-rerunfailures; extra == 'test'
Requires-Dist: pytest-xdist; extra == 'test'
Requires-Dist: pytest>=4.4.0; extra == 'test'
